pypromice/__init__.py
pypromice/core/__init__.py
pypromice/core/dependency_graph.py
pypromice/core/resampling.py
pypromice/core/qc/__init__.py
pypromice/core/qc/github_data_issues.py
pypromice/core/qc/persistence.py
pypromice/core/qc/value_clipping.py
pypromice/core/qc/percentiles/__init__.py
pypromice/core/qc/percentiles/compute_thresholds.py
pypromice/core/qc/percentiles/outlier_detector.py
pypromice/core/qc/percentiles/thresholds.csv
pypromice/core/variables/__init__.py
pypromice/core/variables/air_temperature.py
pypromice/core/variables/gps.py
pypromice/core/variables/humidity.py
pypromice/core/variables/precipitation.py
pypromice/core/variables/pressure_transducer_depth.py
pypromice/core/variables/radiation.py
pypromice/core/variables/station_boom_height.py
pypromice/core/variables/station_pose.py
pypromice/core/variables/wind.py
pypromice/io/__init__.py
pypromice/io/make_metadata_csv.py
pypromice/io/write.py
pypromice/io/bufr/__init__.py
pypromice/io/bufr/bufr_to_csv.py
pypromice/io/bufr/bufr_utilities.py
pypromice/io/bufr/create_bufr_files.py
pypromice/io/bufr/get_bufr.py
pypromice/io/bufr/positions_seed.csv
pypromice/io/bufr/real_time_utilities.py
pypromice/io/bufr/station_configuration.py
pypromice/io/ingest/__init__.py
pypromice/io/ingest/git.py
pypromice/io/ingest/l0.py
pypromice/io/ingest/l0_repository.py
pypromice/io/ingest/toa5.py
pypromice/pipeline/L0toL1.py
pypromice/pipeline/L1toL2.py
pypromice/pipeline/L2toL3.py
pypromice/pipeline/__init__.py
pypromice/pipeline/aws.py
pypromice/pipeline/get_l2.py
pypromice/pipeline/get_l2tol3.py
pypromice/pipeline/join_l2.py
pypromice/pipeline/join_l3.py
pypromice/pipeline/resample.py
pypromice/pipeline/utilities.py
pypromice/resources/__init__.py
pypromice/resources/file_attributes.csv
pypromice/resources/payload_formats.csv
pypromice/resources/payload_types.csv
pypromice/resources/variable_aliases_GC-Net.csv
pypromice/resources/variable_aliases_GlacioBasis.csv
pypromice/resources/variables.csv
pypromice-1.9.0.dist-info/licenses/LICENSE.txt
pypromice-1.9.0.dist-info/METADATA
pypromice-1.9.0.dist-info/WHEEL
pypromice-1.9.0.dist-info/entry_points.txt
pypromice-1.9.0.dist-info/top_level.txt
pypromice-1.9.0.dist-info/RECORD
