Metadata-Version: 2.4
Name: pypromice
Version: 1.9.0
Summary: PROMICE/GC-Net toolbox for processing data from automatic weather stations
Author: GEUS Glaciology and Climate
Project-URL: Homepage, https://github.com/GEUS-Glaciology-and-Climate/pypromice
Project-URL: Documentation, https://pypromice.readthedocs.io
Project-URL: Bug Tracker, https://github.com/GEUS-Glaciology-and-Climate/pypromice/issues
Project-URL: Source Code, https://github.com/GEUS-Glaciology-and-Climate/pypromice
Keywords: promice,gc-net,aws,climate,glaciology,greenland,geus
Classifier: Programming Language :: Python :: 3
Classifier: License :: OSI Approved :: GNU General Public License v2 (GPLv2)
Classifier: Development Status :: 5 - Production/Stable
Classifier: Intended Audience :: Science/Research
Classifier: Natural Language :: English
Classifier: Topic :: Scientific/Engineering
Classifier: Operating System :: OS Independent
Requires-Python: >=3.10
License-File: LICENSE.txt
Requires-Dist: numpy~=1.23
Requires-Dist: pandas>=1.5.0
Requires-Dist: xarray>=2022.6.0
Requires-Dist: attrs
Requires-Dist: toml
Requires-Dist: scipy>=1.9.0
Requires-Dist: Bottleneck
Requires-Dist: netcdf4
Requires-Dist: scikit-learn>=1.1.0
Requires-Dist: pytest
Provides-Extra: bufr
Requires-Dist: eccodes; extra == "bufr"
Provides-Extra: google
Requires-Dist: google-auth; extra == "google"
Requires-Dist: google-auth-oauthlib; extra == "google"
Requires-Dist: google-auth-httplib2; extra == "google"
Requires-Dist: google-api-python-client; extra == "google"
Provides-Extra: all
Requires-Dist: eccodes; extra == "all"
Requires-Dist: google-auth; extra == "all"
Requires-Dist: google-auth-oauthlib; extra == "all"
Requires-Dist: google-auth-httplib2; extra == "all"
Requires-Dist: google-api-python-client; extra == "all"
Dynamic: license-file
